{
  "type": "excalidraw",
  "version": 2,
  "source": "https://excalidraw.com",
  "elements": [
    {
      "type": "rectangle",
      "version": 141,
      "versionNonce": 1001,
      "isDeleted": false,
      "id": "title-box",
      "fillStyle": "solid",
      "strokeWidth": 2,
      "strokeStyle": "solid",
      "roughness": 1,
      "opacity": 100,
      "angle": 0,
      "x": 200,
      "y": 50,
      "strokeColor": "#1e1e1e",
      "backgroundColor": "#4f46e5",
      "width": 400,
      "height": 80,
      "seed": 1001,
      "groupIds": [],
      "frameId": null,
      "roundness": {
        "type": 3
      },
      "boundElements": [],
      "updated": 1001,
      "link": null,
      "locked": false
    },
    {
      "type": "text",
      "version": 141,
      "versionNonce": 1002,
      "isDeleted": false,
      "id": "title-text",
      "fillStyle": "solid",
      "strokeWidth": 2,
      "strokeStyle": "solid",
      "roughness": 1,
      "opacity": 100,
      "angle": 0,
      "x": 280,
      "y": 75,
      "strokeColor": "#ffffff",
      "backgroundColor": "transparent",
      "width": 240,
      "height": 30,
      "seed": 1002,
      "groupIds": [],
      "frameId": null,
      "roundness": null,
      "boundElements": null,
      "updated": 1002,
      "link": null,
      "locked": false,
      "fontSize": 36,
      "fontFamily": 3,
      "text": "Gitary",
      "textAlign": "center",
      "verticalAlign": "middle",
      "containerId": null,
      "originalText": "Gitary",
      "lineHeight": 1.25,
      "baseline": 25
    },
    {
      "type": "text",
      "version": 141,
      "versionNonce": 1003,
      "isDeleted": false,
      "id": "subtitle-text",
      "fillStyle": "solid",
      "strokeWidth": 2,
      "strokeStyle": "solid",
      "roughness": 1,
      "opacity": 100,
      "angle": 0,
      "x": 0,
      "y": 150,
      "strokeColor": "#1e1e1e",
      "backgroundColor": "transparent",
      "width": 800,
      "textAlign": "center",
      "height": 25,
      "seed": 1003,
      "groupIds": [],
      "frameId": null,
      "roundness": null,
      "boundElements": null,
      "updated": 1003,
      "link": null,
      "locked": false,
      "fontSize": 20,
      "fontFamily": 1,
      "text": "Notion-like editing + Excalidraw drawing for your Git repositories",
      "textAlign": "center",
      "verticalAlign": "middle",
      "containerId": null,
      "originalText": "Notion-like editing + Excalidraw drawing for your Git repositories",
      "lineHeight": 1.25,
      "baseline": 18
    },
    {
      "type": "rectangle",
      "version": 141,
      "versionNonce": 1004,
      "isDeleted": false,
      "id": "feature-1",
      "fillStyle": "solid",
      "strokeWidth": 2,
      "strokeStyle": "solid",
      "roughness": 1,
      "opacity": 100,
      "angle": 0,
      "x": 50,
      "y": 220,
      "strokeColor": "#1e1e1e",
      "backgroundColor": "#e0f2fe",
      "width": 180,
      "height": 120,
      "seed": 1004,
      "groupIds": [],
      "frameId": null,
      "roundness": {
        "type": 3
      },
      "boundElements": [
        {
          "type": "text",
          "id": "feature-1-text"
        }
      ],
      "updated": 1004,
      "link": null,
      "locked": false
    },
    {
      "type": "text",
      "version": 141,
      "versionNonce": 1005,
      "isDeleted": false,
      "id": "feature-1-text",
      "fillStyle": "solid",
      "strokeWidth": 2,
      "strokeStyle": "solid",
      "roughness": 1,
      "opacity": 100,
      "angle": 0,
      "x": 75,
      "y": 245,
      "strokeColor": "#1e1e1e",
      "backgroundColor": "transparent",
      "width": 130,
      "height": 70,
      "seed": 1005,
      "groupIds": [],
      "frameId": null,
      "roundness": null,
      "boundElements": null,
      "updated": 1005,
      "link": null,
      "locked": false,
      "fontSize": 16,
      "fontFamily": 1,
      "text": "📝 Notion-like\nEditor\nWYSIWYG",
      "textAlign": "center",
      "verticalAlign": "middle",
      "containerId": "feature-1",
      "originalText": "📝 Notion-like\nEditor\nWYSIWYG",
      "lineHeight": 1.25,
      "baseline": 65
    },
    {
      "type": "rectangle",
      "version": 141,
      "versionNonce": 1006,
      "isDeleted": false,
      "id": "feature-2",
      "fillStyle": "solid",
      "strokeWidth": 2,
      "strokeStyle": "solid",
      "roughness": 1,
      "opacity": 100,
      "angle": 0,
      "x": 310,
      "y": 220,
      "strokeColor": "#1e1e1e",
      "backgroundColor": "#fef3c7",
      "width": 180,
      "height": 120,
      "seed": 1006,
      "groupIds": [],
      "frameId": null,
      "roundness": {
        "type": 3
      },
      "boundElements": [
        {
          "type": "text",
          "id": "feature-2-text"
        }
      ],
      "updated": 1006,
      "link": null,
      "locked": false
    },
    {
      "type": "text",
      "version": 141,
      "versionNonce": 1007,
      "isDeleted": false,
      "id": "feature-2-text",
      "fillStyle": "solid",
      "strokeWidth": 2,
      "strokeStyle": "solid",
      "roughness": 1,
      "opacity": 100,
      "angle": 0,
      "x": 335,
      "y": 245,
      "strokeColor": "#1e1e1e",
      "backgroundColor": "transparent",
      "width": 130,
      "height": 70,
      "seed": 1007,
      "groupIds": [],
      "frameId": null,
      "roundness": null,
      "boundElements": null,
      "updated": 1007,
      "link": null,
      "locked": false,
      "fontSize": 16,
      "fontFamily": 1,
      "text": "🔄 Git Integration\nGitHub/Gitee\nZero Storage",
      "textAlign": "center",
      "verticalAlign": "middle",
      "containerId": "feature-2",
      "originalText": "🔄 Git Integration\nGitHub/Gitee\nZero Storage",
      "lineHeight": 1.25,
      "baseline": 65
    },
    {
      "type": "rectangle",
      "version": 141,
      "versionNonce": 1008,
      "isDeleted": false,
      "id": "feature-3",
      "fillStyle": "solid",
      "strokeWidth": 2,
      "strokeStyle": "solid",
      "roughness": 1,
      "opacity": 100,
      "angle": 0,
      "x": 570,
      "y": 220,
      "strokeColor": "#1e1e1e",
      "backgroundColor": "#dbeafe",
      "width": 180,
      "height": 120,
      "seed": 1008,
      "groupIds": [],
      "frameId": null,
      "roundness": {
        "type": 3
      },
      "boundElements": [
        {
          "type": "text",
          "id": "feature-3-text"
        }
      ],
      "updated": 1008,
      "link": null,
      "locked": false
    },
    {
      "type": "text",
      "version": 141,
      "versionNonce": 1009,
      "isDeleted": false,
      "id": "feature-3-text",
      "fillStyle": "solid",
      "strokeWidth": 2,
      "strokeStyle": "solid",
      "roughness": 1,
      "opacity": 100,
      "angle": 0,
      "x": 595,
      "y": 245,
      "strokeColor": "#1e1e1e",
      "backgroundColor": "transparent",
      "width": 130,
      "height": 70,
      "seed": 1009,
      "groupIds": [],
      "frameId": null,
      "roundness": null,
      "boundElements": null,
      "updated": 1009,
      "link": null,
      "locked": false,
      "fontSize": 16,
      "fontFamily": 1,
      "text": "🎨 VS Code\nStyle UI\nProfessional",
      "textAlign": "center",
      "verticalAlign": "middle",
      "containerId": "feature-3",
      "originalText": "🎨 VS Code\nStyle UI\nProfessional",
      "lineHeight": 1.25,
      "baseline": 65
    },
    {
      "type": "rectangle",
      "version": 141,
      "versionNonce": 1010,
      "isDeleted": false,
      "id": "feature-4",
      "fillStyle": "solid",
      "strokeWidth": 2,
      "strokeStyle": "solid",
      "roughness": 1,
      "opacity": 100,
      "angle": 0,
      "x": 180,
      "y": 380,
      "strokeColor": "#1e1e1e",
      "backgroundColor": "#fce7f3",
      "width": 180,
      "height": 120,
      "seed": 1010,
      "groupIds": [],
      "frameId": null,
      "roundness": {
        "type": 3
      },
      "boundElements": [
        {
          "type": "text",
          "id": "feature-4-text"
        }
      ],
      "updated": 1010,
      "link": null,
      "locked": false
    },
    {
      "type": "text",
      "version": 141,
      "versionNonce": 1011,
      "isDeleted": false,
      "id": "feature-4-text",
      "fillStyle": "solid",
      "strokeWidth": 2,
      "strokeStyle": "solid",
      "roughness": 1,
      "opacity": 100,
      "angle": 0,
      "x": 205,
      "y": 405,
      "strokeColor": "#1e1e1e",
      "backgroundColor": "transparent",
      "width": 130,
      "height": 70,
      "seed": 1011,
      "groupIds": [],
      "frameId": null,
      "roundness": null,
      "boundElements": null,
      "updated": 1011,
      "link": null,
      "locked": false,
      "fontSize": 16,
      "fontFamily": 1,
      "text": "🔍 Full-Text\nSearch\nFast & Accurate",
      "textAlign": "center",
      "verticalAlign": "middle",
      "containerId": "feature-4",
      "originalText": "🔍 Full-Text\nSearch\nFast & Accurate",
      "lineHeight": 1.25,
      "baseline": 65
    },
    {
      "type": "rectangle",
      "version": 141,
      "versionNonce": 1012,
      "isDeleted": false,
      "id": "feature-5",
      "fillStyle": "solid",
      "strokeWidth": 2,
      "strokeStyle": "solid",
      "roughness": 1,
      "opacity": 100,
      "angle": 0,
      "x": 440,
      "y": 380,
      "strokeColor": "#1e1e1e",
      "backgroundColor": "#dcfce7",
      "width": 180,
      "height": 120,
      "seed": 1012,
      "groupIds": [],
      "frameId": null,
      "roundness": {
        "type": 3
      },
      "boundElements": [
        {
          "type": "text",
          "id": "feature-5-text"
        }
      ],
      "updated": 1012,
      "link": null,
      "locked": false
    },
    {
      "type": "text",
      "version": 141,
      "versionNonce": 1013,
      "isDeleted": false,
      "id": "feature-5-text",
      "fillStyle": "solid",
      "strokeWidth": 2,
      "strokeStyle": "solid",
      "roughness": 1,
      "opacity": 100,
      "angle": 0,
      "x": 465,
      "y": 405,
      "strokeColor": "#1e1e1e",
      "backgroundColor": "transparent",
      "width": 130,
      "height": 70,
      "seed": 1013,
      "groupIds": [],
      "frameId": null,
      "roundness": null,
      "boundElements": null,
      "updated": 1013,
      "link": null,
      "locked": false,
      "fontSize": 16,
      "fontFamily": 1,
      "text": "🎨 Excalidraw\nDrawing\nDiagrams & Sketches",
      "textAlign": "center",
      "verticalAlign": "middle",
      "containerId": "feature-5",
      "originalText": "🎨 Excalidraw\nDrawing\nDiagrams & Sketches",
      "lineHeight": 1.25,
      "baseline": 65
    },
    {
      "type": "ellipse",
      "version": 141,
      "versionNonce": 1014,
      "isDeleted": false,
      "id": "advantage-box",
      "fillStyle": "solid",
      "strokeWidth": 2,
      "strokeStyle": "solid",
      "roughness": 1,
      "opacity": 100,
      "angle": 0,
      "x": 250,
      "y": 540,
      "strokeColor": "#059669",
      "backgroundColor": "#d1fae5",
      "width": 300,
      "height": 100,
      "seed": 1014,
      "groupIds": [],
      "frameId": null,
      "roundness": null,
      "boundElements": [
        {
          "type": "text",
          "id": "advantage-text"
        }
      ],
      "updated": 1014,
      "link": null,
      "locked": false
    },
    {
      "type": "text",
      "version": 141,
      "versionNonce": 1015,
      "isDeleted": false,
      "id": "advantage-text",
      "fillStyle": "solid",
      "strokeWidth": 2,
      "strokeStyle": "solid",
      "roughness": 1,
      "opacity": 100,
      "angle": 0,
      "x": 300,
      "y": 570,
      "strokeColor": "#059669",
      "backgroundColor": "transparent",
      "width": 200,
      "height": 40,
      "seed": 1015,
      "groupIds": [],
      "frameId": null,
      "roundness": null,
      "boundElements": null,
      "updated": 1015,
      "link": null,
      "locked": false,
      "fontSize": 18,
      "fontFamily": 1,
      "text": "✅ Complete Data Control\n✅ No Service Dependency",
      "textAlign": "center",
      "verticalAlign": "middle",
      "containerId": "advantage-box",
      "originalText": "✅ Complete Data Control\n✅ No Service Dependency",
      "lineHeight": 1.25,
      "baseline": 35
    }
  ],
  "appState": {
    "gridSize": null,
    "viewBackgroundColor": "#ffffff"
  },
  "files": {}
}
